README.md
setup.py
SpecLab/__init__.py
SpecLab.egg-info/PKG-INFO
SpecLab.egg-info/SOURCES.txt
SpecLab.egg-info/dependency_links.txt
SpecLab.egg-info/requires.txt
SpecLab.egg-info/top_level.txt
SpecLab/aux/__init__.py
SpecLab/aux/pyqtgraph_modifications.tar.gz
SpecLab/aux/param_files/__init__.py
SpecLab/aux/param_files/imXam_param.dat
SpecLab/aux/param_files/imXam_param.default.dat
SpecLab/aux/param_files/imXam_param_ARCES.dat
SpecLab/cfg/SpecLab_config.py
SpecLab/cfg/epar_imXam.py
SpecLab/doc/CHANGELOG.txt
SpecLab/doc/KNOWN_ISSUES.txt
SpecLab/doc/LICENSE.txt
SpecLab/doc/README.md
SpecLab/doc/__init__.py
SpecLab/gen/SpecLabFunctions.py
SpecLab/gen/__init__.py
SpecLab/gen/globals.py
SpecLab/gen/myfunc.py
SpecLab/imXam/__init__.py
SpecLab/imXam/imXam.py