Metadata-Version: 2.1
Name: SpecLab
Version: 4.2.2
Summary: IRAF imexam+DS9 alternative for Python
Home-page: http://pypi.python.org/pypi/SpecLab/
Author: A. F. Kowalski
Author-email: adam.f.kowalski@colorado.edu
